deel/datasets/__init__.py
deel/datasets/__main__.py
deel/datasets/dataset.py
deel/datasets/settings.py
deel/datasets/providers/__init__.py
deel/datasets/providers/exceptions.py
deel/datasets/providers/ftp_providers.py
deel/datasets/providers/gcloud_provider.py
deel/datasets/providers/http_providers.py
deel/datasets/providers/local_as_provider.py
deel/datasets/providers/local_provider.py
deel/datasets/providers/provider.py
deel/datasets/providers/remote_provider.py
deel/datasets/providers/webdav_provider.py
deel/datasets/utils/__init__.py
deel/datasets/utils/numpy_utils.py
deel/datasets/utils/supervised.py
deel/datasets/utils/tensorflow_utils.py
deel/datasets/utils/torch_utils.py
deel/datasets/utils/unsupervised.py
deel_datasets-0.0.7.dist-info/LICENSE
deel_datasets-0.0.7.dist-info/METADATA
deel_datasets-0.0.7.dist-info/WHEEL
deel_datasets-0.0.7.dist-info/top_level.txt
deel_datasets-0.0.7.dist-info/RECORD
